AUTHORS
CHANGES
LICENSE
MANIFEST.in
README.rst
setup.cfg
setup.py
django_safedelete_e2e.egg-info/PKG-INFO
django_safedelete_e2e.egg-info/SOURCES.txt
django_safedelete_e2e.egg-info/dependency_links.txt
django_safedelete_e2e.egg-info/requires.txt
django_safedelete_e2e.egg-info/top_level.txt
safedelete/__init__.py
safedelete/admin.py
safedelete/managers.py
safedelete/models.py
safedelete/settings.py
safedelete/shortcuts.py
safedelete/tests.py
safedelete/utils.py
safedelete/locale/fr/LC_MESSAGES/django.po
safedelete/static/safedelete/admin.css
safedelete/templates/safedelete/undelete_selected_confirmation.html