Metadata-Version: 2.1
Name: django-safedelete-e2e
Version: 3.0.0
Summary: Mask your objects instead of deleting them from your database.
Home-page: https://github.com/makinacorpus/django-safedelete
Author: Rounak Kabra
Author-email: rounak.kabra@e2enetowrks.com
License: BSD
Keywords: django,delete,safedelete,softdelete
Classifier: Framework :: Django
Classifier: Intended Audience :: Developers
Classifier: License :: OSI Approved :: BSD License
Classifier: Programming Language :: Python
Classifier: Programming Language :: Python :: 2
Classifier: Programming Language :: Python :: 2.7
Classifier: Programming Language :: Python :: 3
Classifier: Programming Language :: Python :: 3.3
Classifier: Programming Language :: Python :: 3.4
Classifier: Programming Language :: Python :: 3.5
Classifier: Programming Language :: Python :: 3.6
Classifier: Programming Language :: Python :: 3.7
Classifier: Programming Language :: Python :: 3.8
Classifier: Development Status :: 4 - Beta
License-File: LICENSE
License-File: AUTHORS
